{"expireTime":9007200848238794000,"key":"transformer-remark-markdown-html-ast-659708595f636ffdfd57d08b6f6a480f--","val":{"type":"root","children":[{"type":"element","tagName":"p","properties":{},"children":[{"type":"text","value":"Comment concevoir de façon responsable des services ou des produits numériques ? Telle est la question centrale que nous posons édition après édition à Ethics by design. Une question toujours centrale dans une année 2020 largement inédite tant par les évènements mondiaux que nous affrontons que par l’engouement général du monde de la conception numérique pour cette problématique.","position":{"start":{"line":2,"column":1,"offset":1},"end":{"line":2,"column":383,"offset":383}}}],"position":{"start":{"line":2,"column":1,"offset":1},"end":{"line":2,"column":383,"offset":383}}},{"type":"text","value":"\n"},{"type":"element","tagName":"p","properties":{},"children":[{"type":"text","value":"Au travers de conférences et ateliers donnés par des professionnels du design et chercheurs, vous allez pouvoir explorer le sujet de la conception repsonsable au travers du design, de l’économie, de la stratégie, de la formation, de la politique d’innovation.","position":{"start":{"line":4,"column":1,"offset":385},"end":{"line":4,"column":260,"offset":644}}}],"position":{"start":{"line":4,"column":1,"offset":385},"end":{"line":4,"column":260,"offset":644}}}],"position":{"start":{"line":1,"column":1,"offset":0},"end":{"line":5,"column":1,"offset":645}}}}